xyz_qcloud/__init__.py
xyz_qcloud/asr.py
xyz_qcloud/cos.py
xyz_qcloud/nlp.py
xyz_qcloud/ssl.py
xyz_qcloud/sts.py
xyz_qcloud/utils.py
xyz_qcloud/vod.py
xyz_qcloud-0.2.1.dist-info/METADATA
xyz_qcloud-0.2.1.dist-info/WHEEL
xyz_qcloud-0.2.1.dist-info/top_level.txt
xyz_qcloud-0.2.1.dist-info/RECORD
