Metadata-Version: 2.1
Name: xyz-qcloud
Version: 0.2.1
Summary: qcloud utils
Home-page: https://github.com/szuprefix/py-xyz-qcloud
Author: XYZSaas
Author-email: szuprefix@126.com
License: MIT
Classifier: Environment :: Web Environment
Classifier: Intended Audience :: Developers
Classifier: Operating System :: OS Independent
Classifier: Topic :: Text Processing :: Indexing
Classifier: Topic :: Utilities
Classifier: Topic :: Internet
Classifier: Topic :: Software Development :: Libraries :: Python Modules
Classifier: Programming Language :: Python
Classifier: Programming Language :: Python :: 2
Classifier: Programming Language :: Python :: 2.7
Requires-Dist: django>=1.11.2
Requires-Dist: vod-python-sdk
Requires-Dist: tencentcloud-sdk-python
